threadlet/__about__.py
threadlet/__init__.py
threadlet-3.2.1.dist-info/METADATA
threadlet-3.2.1.dist-info/WHEEL
threadlet-3.2.1.dist-info/licenses/LICENSE
threadlet-3.2.1.dist-info/RECORD
