Metadata-Version: 2.3
Name: threadlet
Version: 3.2.1
Summary: Convenient threading and improved ThreadPoolExecutor
Project-URL: Documentation, https://github.com/jackcvr/threadlet#readme
Project-URL: Issues, https://github.com/jackcvr/threadlet/issues
Project-URL: Source, https://github.com/jackcvr/threadlet
Author-email: Andrii Kuzmin <jack.cvr@gmail.com>
License-Expression: MIT
License-File: LICENSE
Keywords: thread pool,threads
Classifier: Development Status :: 4 - Beta
Classifier: Programming Language :: Python
Classifier: Programming Language :: Python :: 3.7
Classifier: Programming Language :: Python :: 3.8
Classifier: Programming Language :: Python :: 3.9
Classifier: Programming Language :: Python :: 3.10
Classifier: Programming Language :: Python :: 3.11
Classifier: Programming Language :: Python :: 3.12
Classifier: Programming Language :: Python :: Implementation :: CPython
Classifier: Programming Language :: Python :: Implementation :: PyPy
Requires-Python: >=3.7
